docs/Makefile
docs/changelog.rst
docs/conf.py
docs/index.rst
docs/make.bat
docs/references/client.rst
docs/references/index.rst
docs/references/misc.rst
docs/references/model.rst
tdworkflow/__init__.py
tdworkflow/attempt.py
tdworkflow/client.py
tdworkflow/exceptions.py
tdworkflow/log.py
tdworkflow/project.py
tdworkflow/py.typed
tdworkflow/resource.py
tdworkflow/revision.py
tdworkflow/schedule.py
tdworkflow/session.py
tdworkflow/task.py
tdworkflow/util.py
tdworkflow/workflow.py
tdworkflow-0.10.1.dist-info/licenses/LICENSE
tests/test_client.py
tests/test_util.py
tests/resources/sample_project/.digdag
tests/resources/sample_project/main.dig
tests/resources/sample_project/ignore_dir/dummy
tests/resources/sample_project/py_scripts/exec.py
tests/resources/sample_project/py_scripts/__ignoredir__/dummy
tdworkflow-0.10.1.dist-info/METADATA
tdworkflow-0.10.1.dist-info/WHEEL
tdworkflow-0.10.1.dist-info/top_level.txt
tdworkflow-0.10.1.dist-info/RECORD
