Metadata-Version: 2.4
Name: tdworkflow
Version: 0.10.1
Summary: Unofficial Treasure Workflow API client
Author-email: Aki Ariga <chezou@gmail.com>
Maintainer-email: Aki Ariga <chezou@gmail.com>
License: 
Project-URL: Homepage, https://github.com/chezou/tdworkflow
Project-URL: Bug Reports, https://github.com/chezou/tdworkflow/issues
Project-URL: Funding, https://github.com/sponsors/chezou
Classifier: Development Status :: 4 - Beta
Classifier: Intended Audience :: Developers
Classifier: Operating System :: OS Independent
Classifier: License :: OSI Approved :: Apache Software License
Classifier: Topic :: Database
Classifier: Programming Language :: Python :: 3
Classifier: Programming Language :: Python :: 3.10
Classifier: Programming Language :: Python :: 3.11
Classifier: Programming Language :: Python :: 3.12
Classifier: Programming Language :: Python :: 3.13
Classifier: Programming Language :: Python :: 3.14
Requires-Python: >=3.10
License-File: LICENSE
Requires-Dist: requests
Requires-Dist: mypy-extensions
Provides-Extra: dev
Requires-Dist: pytest; extra == "dev"
Requires-Dist: pytest-mock; extra == "dev"
Requires-Dist: ruff; extra == "dev"
Requires-Dist: ty; extra == "dev"
Provides-Extra: doc
Requires-Dist: sphinx; extra == "doc"
Requires-Dist: sphinx_rtd_theme; extra == "doc"
Dynamic: license-file
